velatir/__init__.py
velatir/client.py
velatir/decorators.py
velatir/exceptions.py
velatir/models.py
velatir/utils.py
velatir-1.0.4.dist-info/METADATA
velatir-1.0.4.dist-info/WHEEL
velatir-1.0.4.dist-info/top_level.txt
velatir-1.0.4.dist-info/RECORD
