Metadata-Version: 2.4
Name: velatir
Version: 1.0.4
Summary: Python SDK for Velatir - AI function monitoring and approval
Home-page: https://www.velatir.com
Author: Velatir
Author-email: Velatir <hello@velatir.com>
Project-URL: Homepage, https://www.velatir.com
Project-URL: Documentation, https://www.velatir.com/docs/
Project-URL: Issues, https://github.com/velatir/velatir-sdk/issues
Classifier: Development Status :: 4 - Beta
Classifier: Intended Audience :: Developers
Classifier: License :: OSI Approved :: MIT License
Classifier: Programming Language :: Python :: 3
Classifier: Programming Language :: Python :: 3.7
Classifier: Programming Language :: Python :: 3.8
Classifier: Programming Language :: Python :: 3.9
Classifier: Programming Language :: Python :: 3.10
Classifier: Programming Language :: Python :: 3.11
Classifier: Programming Language :: Python :: 3.12
Classifier: Programming Language :: Python :: 3.13
Classifier: Topic :: Software Development :: Libraries :: Python Modules
Requires-Python: >=3.7
Requires-Dist: httpx>=0.23.0
Requires-Dist: pydantic>=1.9.0
Requires-Dist: tenacity>=8.0.0
Dynamic: author
Dynamic: home-page
Dynamic: requires-python
